CHANGELOG.md
LICENSE
README.md
django_temporalio/__init__.py
django_temporalio/apps.py
django_temporalio/client.py
django_temporalio/conf.py
django_temporalio/registry.py
django_temporalio/utils.py
django_temporalio/management/__init__.py
django_temporalio/management/commands/__init__.py
django_temporalio/management/commands/show_temporalio_queue_registry.py
django_temporalio/management/commands/start_temporalio_worker.py
django_temporalio/management/commands/sync_temporalio_schedules.py
django_temporalio/tests/__init__.py
django_temporalio/tests/test_init_client.py
django_temporalio/tests/test_settings.py
django_temporalio/tests/management_commands/__init__.py
django_temporalio/tests/management_commands/test_show_temporalio_queue_registry.py
django_temporalio/tests/management_commands/test_start_temporalio_worker.py
django_temporalio/tests/management_commands/test_sync_temporal_schedules.py
django_temporalio/tests/registry/__init__.py
django_temporalio/tests/registry/test_get_queue_registry.py
django_temporalio/tests/registry/test_queue_activities.py
django_temporalio/tests/registry/test_queue_workflows.py
django_temporalio/tests/registry/test_schedules.py
django_temporalio/tests/utils/__init__.py
django_temporalio/tests/utils/test_autodiscover_modules.py
django_temporalio-2.0.0.dist-info/METADATA
django_temporalio-2.0.0.dist-info/WHEEL
django_temporalio-2.0.0.dist-info/licenses/LICENSE
django_temporalio-2.0.0.dist-info/RECORD
